[
  {
    "amount": 3.99,
    "category": "Food Drinks",
    "counterPartyCountry": "US",
    "counterPartyName": "McDonalds",
    "creditDebitIndicator": "DBIT",
    "currency": "USD",
    "reference": "czyo9c2n7z",
    "type": "POS",
    "typeGroup": "Payment"
  },
  {
    "amount": 14.99,
    "category": "Hobbies Entertainment",
    "counterPartyCountry": "US",
    "counterPartyName": "Spotify",
    "creditDebitIndicator": "DBIT",
    "currency": "USD",
    "reference": "czyo9c2n7z",
    "type": "POS",
    "typeGroup": "Payment"
  },
  {
    "amount": 1199.99,
    "category": "Shopping",
    "counterPartyCountry": "US",
    "counterPartyName": "Best Buy",
    "creditDebitIndicator": "DBIT",
    "currency": "USD",
    "reference": "czyo9c2n7z",
    "type": "POS",
    "typeGroup": "Payment",
    "description": "Anniversary Gift"
  },
  {
    "amount": 4000,
    "category": "Income",
    "counterPartyCountry": "US",
    "counterPartyName": "Monthly Salary",
    "creditDebitIndicator": "CRDT",
    "currency": "USD",
    "reference": "czyo9c2n7z",
    "type": "POS",
    "typeGroup": "Payment"
  },
  {
    "amount": 239.99,
    "category": "Shopping",
    "counterPartyCountry": "US",
    "counterPartyName": "Amazon",
    "creditDebitIndicator": "DBIT",
    "currency": "USD",
    "reference": "czyo9c2n7z",
    "type": "POS",
    "typeGroup": "Payment",
    "description": "Happy Birthday Gift"
  },
  {
    "amount": 80,
    "category": "Bills Utilities",
    "counterPartyCountry": "US",
    "counterPartyName": "AT&T",
    "creditDebitIndicator": "DBIT",
    "currency": "USD",
    "reference": "czyo9c2n7z",
    "type": "POS",
    "typeGroup": "Payment"
  },
  {
    "amount": 160,
    "category": "Shopping",
    "counterPartyCountry": "US",
    "counterPartyName": "Nike",
    "creditDebitIndicator": "DBIT",
    "currency": "USD",
    "reference": "czyo9c2n7z",
    "type": "POS",
    "typeGroup": "Payment"
  },
  {
    "amount": 1500,
    "category": "Bills Utilities",
    "counterPartyCountry": "US",
    "counterPartyName": "Home Rent",
    "creditDebitIndicator": "DBIT",
    "currency": "USD",
    "reference": "czyo9c2n7z",
    "type": "POS",
    "typeGroup": "Payment"
  },
  {
    "amount": 71,
    "category": "Health Beauty",
    "counterPartyCountry": "US",
    "counterPartyName": "Gloss Makeup & Beauty Studio",
    "creditDebitIndicator": "DBIT",
    "currency": "USD",
    "reference": "czyo9c2n7z",
    "type": "POS",
    "typeGroup": "Payment"
  },
  {
    "amount": 76,
    "category": "Bills Utilities",
    "counterPartyCountry": "US",
    "counterPartyName": "NextEra Energy",
    "creditDebitIndicator": "DBIT",
    "currency": "USD",
    "reference": "czyo9c2n7z",
    "type": "POS",
    "typeGroup": "Payment"
  },
  {
    "amount": 250,
    "category": "Transfers",
    "counterPartyCountry": "US",
    "counterPartyName": "Bank of America",
    "creditDebitIndicator": "CRDT",
    "currency": "USD",
    "reference": "czyo9c2n7z",
    "type": "POS",
    "typeGroup": "Payment"
  },
  {
    "amount": 85,
    "category": "Transport",
    "counterPartyCountry": "US",
    "counterPartyName": "ARCO Gas Station",
    "creditDebitIndicator": "DBIT",
    "currency": "USD",
    "reference": "czyo9c2n7z",
    "type": "POS",
    "typeGroup": "Payment"
  },
  {
    "amount": 4.45,
    "category": "Food Drinks",
    "counterPartyCountry": "US",
    "counterPartyName": "Starbucks",
    "creditDebitIndicator": "DBIT",
    "currency": "USD",
    "reference": "czyo9c2n7z",
    "type": "POS",
    "typeGroup": "Payment"
  },
  {
    "amount": 76,
    "category": "Bills Utilities",
    "counterPartyCountry": "US",
    "counterPartyName": "NextEra Energy",
    "creditDebitIndicator": "DBIT",
    "currency": "USD",
    "reference": "czyo9c2n7z",
    "type": "POS",
    "typeGroup": "Payment"
  },
  {
    "amount": 90,
    "category": "Shopping",
    "counterPartyCountry": "US",
    "counterPartyName": "Under Armour",
    "creditDebitIndicator": "DBIT",
    "currency": "USD",
    "reference": "czyo9c2n7z",
    "type": "POS",
    "typeGroup": "Payment"
  },
  {
    "amount": 56.87,
    "category": "Health Beauty",
    "counterPartyCountry": "US",
    "counterPartyName": "Harmon Face Values",
    "creditDebitIndicator": "DBIT",
    "currency": "USD",
    "reference": "czyo9c2n7z",
    "type": "POS",
    "typeGroup": "Payment"
  },
  {
    "amount": 12.99,
    "category": "Hobbies Entertainment",
    "counterPartyCountry": "US",
    "counterPartyName": "Netflix",
    "creditDebitIndicator": "DBIT",
    "currency": "USD",
    "reference": "czyo9c2n7z",
    "type": "POS",
    "typeGroup": "Payment"
  },
  {
    "amount": 36.39,
    "category": "Shopping",
    "counterPartyCountry": "US",
    "counterPartyName": "Albertsons LLC",
    "creditDebitIndicator": "DBIT",
    "currency": "USD",
    "reference": "czyo9c2n7z",
    "type": "POS",
    "typeGroup": "Payment"
  },
  {
    "amount": 400,
    "category": "Transfers",
    "counterPartyCountry": "US",
    "counterPartyName": "Brittney T. Smith",
    "creditDebitIndicator": "CRDT",
    "currency": "USD",
    "reference": "czyo9c2n7z",
    "type": "POS",
    "typeGroup": "Payment"
  },
  {
    "amount": 54,
    "category": "Transport",
    "counterPartyCountry": "US",
    "counterPartyName": "Uber",
    "creditDebitIndicator": "DBIT",
    "currency": "USD",
    "reference": "czyo9c2n7z",
    "type": "POS",
    "typeGroup": "Payment"
  },
  {
    "amount": 90,
    "category": "Shopping",
    "counterPartyCountry": "US",
    "counterPartyName": "Nike",
    "creditDebitIndicator": "DBIT",
    "currency": "USD",
    "reference": "czyo9c2n7z",
    "type": "POS",
    "typeGroup": "Payment"
  },
  {
    "amount": 159,
    "category": "Shopping",
    "counterPartyCountry": "US",
    "counterPartyName": "Apple Store",
    "creditDebitIndicator": "DBIT",
    "currency": "USD",
    "reference": "czyo9c2n7z",
    "type": "POS",
    "typeGroup": "Payment"
  },
  {
    "amount": 202.95,
    "category": "Home",
    "counterPartyCountry": "US",
    "counterPartyName": "Gardeners",
    "creditDebitIndicator": "DBIT",
    "currency": "USD",
    "reference": "czyo9c2n7z",
    "type": "POS",
    "typeGroup": "Payment"
  },
  {
    "amount": 295,
    "category": "Shopping",
    "counterPartyCountry": "US",
    "counterPartyName": "Burro Kids",
    "creditDebitIndicator": "DBIT",
    "currency": "USD",
    "reference": "czyo9c2n7z",
    "type": "POS",
    "typeGroup": "Payment"
  },
  {
    "amount": 43,
    "category": "Health Beauty",
    "counterPartyCountry": "US",
    "counterPartyName": "Hammer & Nails",
    "creditDebitIndicator": "DBIT",
    "currency": "USD",
    "reference": "czyo9c2n7z",
    "type": "POS",
    "typeGroup": "Payment"
  },
  {
    "amount": 35,
    "category": "Shopping",
    "counterPartyCountry": "US",
    "counterPartyName": "Amazon",
    "creditDebitIndicator": "DBIT",
    "currency": "USD",
    "reference": "czyo9c2n7z",
    "type": "POS",
    "typeGroup": "Payment"
  },
  {
    "amount": 3.75,
    "category": "Food Drinks",
    "counterPartyCountry": "US",
    "counterPartyName": "Starbucks",
    "creditDebitIndicator": "DBIT",
    "currency": "USD",
    "reference": "czyo9c2n7z",
    "type": "POS",
    "typeGroup": "Payment"
  },
  {
    "amount": 249.99,
    "category": "Shopping",
    "counterPartyCountry": "US",
    "counterPartyName": "IKEA",
    "creditDebitIndicator": "DBIT",
    "currency": "USD",
    "reference": "czyo9c2n7z",
    "type": "POS",
    "typeGroup": "Payment"
  },
  {
    "amount": 10,
    "category": "Shopping",
    "counterPartyCountry": "US",
    "counterPartyName": "GameStop",
    "creditDebitIndicator": "DBIT",
    "currency": "USD",
    "reference": "czyo9c2n7z",
    "type": "POS",
    "typeGroup": "Payment"
  },
  {
    "amount": 112.05,
    "category": "Shopping",
    "counterPartyCountry": "US",
    "counterPartyName": "Walmart",
    "creditDebitIndicator": "DBIT",
    "currency": "USD",
    "reference": "czyo9c2n7z",
    "type": "POS",
    "typeGroup": "Payment"
  },
  {
    "amount": 24.47,
    "category": "Health Beauty",
    "counterPartyCountry": "US",
    "counterPartyName": "Benefit Cosmetics",
    "creditDebitIndicator": "DBIT",
    "currency": "USD",
    "reference": "czyo9c2n7z",
    "type": "POS",
    "typeGroup": "Payment"
  },
  {
    "amount": 149,
    "category": "Shopping",
    "counterPartyCountry": "US",
    "counterPartyName": "Tommy Hilfiger",
    "creditDebitIndicator": "DBIT",
    "currency": "USD",
    "reference": "czyo9c2n7z",
    "type": "POS",
    "typeGroup": "Payment"
  },
  {
    "amount": 20,
    "category": "Transfers",
    "counterPartyCountry": "US",
    "counterPartyName": "Pamela W. Green",
    "creditDebitIndicator": "DBIT",
    "currency": "USD",
    "reference": "czyo9c2n7z",
    "type": "POS",
    "typeGroup": "Payment"
  },
  {
    "amount": 125,
    "category": "Food Drinks",
    "counterPartyCountry": "US",
    "counterPartyName": "Saison",
    "creditDebitIndicator": "DBIT",
    "currency": "USD",
    "reference": "czyo9c2n7z",
    "type": "POS",
    "typeGroup": "Payment"
  },
  {
    "amount": 35,
    "category": "Other Income",
    "counterPartyCountry": "US",
    "counterPartyName": "PayPal",
    "creditDebitIndicator": "CRDT",
    "currency": "USD",
    "reference": "czyo9c2n7z",
    "type": "POS",
    "typeGroup": "Payment"
  },
  {
    "amount": 97.5,
    "category": "Transport",
    "counterPartyCountry": "US",
    "counterPartyName": "Metro Subscription",
    "creditDebitIndicator": "DBIT",
    "currency": "USD",
    "reference": "czyo9c2n7z",
    "type": "POS",
    "typeGroup": "Payment"
  },
  {
    "amount": 120,
    "category": "Health Beauty",
    "counterPartyCountry": "US",
    "counterPartyName": "Hand & Stone Spa",
    "creditDebitIndicator": "DBIT",
    "currency": "USD",
    "reference": "czyo9c2n7z",
    "type": "POS",
    "typeGroup": "Payment",
    "description": "Full Body Massage 2 hours"
  },
  {
    "amount": 156.75,
    "category": "Shopping",
    "counterPartyCountry": "US",
    "counterPartyName": "The Home Depot",
    "creditDebitIndicator": "DBIT",
    "currency": "USD",
    "reference": "czyo9c2n7z",
    "type": "POS",
    "typeGroup": "Payment",
    "description": "Room renovation"
  },
  {
    "amount": 87.65,
    "category": "Shopping",
    "counterPartyCountry": "US",
    "counterPartyName": "Walmart",
    "creditDebitIndicator": "DBIT",
    "currency": "USD",
    "reference": "czyo9c2n7z",
    "type": "POS",
    "typeGroup": "Payment"
  },
  {
    "amount": 4.99,
    "category": "Bills Utilities",
    "counterPartyCountry": "US",
    "counterPartyName": "Apple Store",
    "creditDebitIndicator": "DBIT",
    "currency": "USD",
    "reference": "czyo9c2n7z",
    "type": "POS",
    "typeGroup": "Payment",
    "description": "iCloud subscription"
  },
  {
    "amount": 29.99,
    "category": "Bills Utilities",
    "counterPartyCountry": "US",
    "counterPartyName": "LinkedIn",
    "creditDebitIndicator": "DBIT",
    "currency": "USD",
    "reference": "czyo9c2n7z",
    "type": "POS",
    "typeGroup": "Payment"
  },
  {
    "amount": 48,
    "category": "Transfers",
    "counterPartyCountry": "US",
    "counterPartyName": "John Doe",
    "creditDebitIndicator": "CRDT",
    "currency": "USD",
    "reference": "czyo9c2n7z",
    "type": "POS",
    "typeGroup": "Payment"
  },
  {
    "amount": 500,
    "category": "Transfers",
    "counterPartyCountry": "US",
    "counterPartyName": "Coinbase Payments, LTD",
    "creditDebitIndicator": "DBIT",
    "currency": "USD",
    "reference": "czyo9c2n7z",
    "type": "POS",
    "typeGroup": "Payment"
  },
  {
    "amount": 300,
    "category": "Transfers",
    "counterPartyCountry": "US",
    "counterPartyName": "Savings Account",
    "creditDebitIndicator": "DBIT",
    "currency": "USD",
    "reference": "czyo9c2n7z",
    "type": "POS",
    "typeGroup": "Payment"
  },
  {
    "amount": 35.49,
    "category": "Transport",
    "counterPartyCountry": "US",
    "counterPartyName": "Lyft",
    "creditDebitIndicator": "DBIT",
    "currency": "USD",
    "reference": "czyo9c2n7z",
    "type": "POS",
    "typeGroup": "Payment",
    "description": "Airport Transfer"
  },
  {
    "amount": 213,
    "category": "Shopping",
    "counterPartyCountry": "US",
    "counterPartyName": "Calvin Klein",
    "creditDebitIndicator": "DBIT",
    "currency": "USD",
    "reference": "czyo9c2n7z",
    "type": "POS",
    "typeGroup": "Payment"
  },
  {
    "amount": 17.13,
    "category": "Shopping",
    "counterPartyCountry": "US",
    "counterPartyName": "eBay",
    "creditDebitIndicator": "DBIT",
    "currency": "USD",
    "reference": "czyo9c2n7z",
    "type": "POS",
    "typeGroup": "Payment"
  },
  {
    "amount": 450,
    "category": "Transfers",
    "counterPartyCountry": "US",
    "counterPartyName": "Backbase Bank",
    "creditDebitIndicator": "DBIT",
    "currency": "USD",
    "reference": "czyo9c2n7z",
    "type": "POS",
    "typeGroup": "Payment",
    "description": "Credit card payment"
  },
  {
    "amount": 150,
    "category": "Bills Utilities",
    "counterPartyCountry": "US",
    "counterPartyName": "Lifetime Healthcare Group",
    "creditDebitIndicator": "DBIT",
    "currency": "USD",
    "reference": "czyo9c2n7z",
    "type": "POS",
    "typeGroup": "Payment"
  },
  {
    "amount": 27.54,
    "category": "Food Drinks",
    "counterPartyCountry": "US",
    "counterPartyName": "Domino's",
    "creditDebitIndicator": "DBIT",
    "currency": "USD",
    "reference": "czyo9c2n7z",
    "type": "POS",
    "typeGroup": "Payment"
  },
  {
    "amount": 18.75,
    "category": "Food Drinks",
    "counterPartyCountry": "US",
    "counterPartyName": "La Taqueria",
    "creditDebitIndicator": "DBIT",
    "currency": "USD",
    "reference": "czyo9c2n7z",
    "type": "POS",
    "typeGroup": "Payment"
  },
  {
    "amount": 14.5,
    "category": "Food Drinks",
    "counterPartyCountry": "US",
    "counterPartyName": "Burrito's Anonymous",
    "creditDebitIndicator": "DBIT",
    "currency": "USD",
    "reference": "czyo9c2n7z",
    "type": "POS",
    "typeGroup": "Payment"
  },
  {
    "amount": 66.8,
    "category": "Food Drinks",
    "counterPartyCountry": "US",
    "counterPartyName": "Whole Foods",
    "creditDebitIndicator": "DBIT",
    "currency": "USD",
    "reference": "czyo9c2n7z",
    "type": "POS",
    "typeGroup": "Payment"
  },
  {
    "amount": 8.95,
    "category": "Food Drinks",
    "counterPartyCountry": "US",
    "counterPartyName": "McDonalds",
    "creditDebitIndicator": "DBIT",
    "currency": "USD",
    "reference": "czyo9c2n7z",
    "type": "POS",
    "typeGroup": "Payment"
  },
  {
    "amount": 22.5,
    "category": "Shopping",
    "counterPartyCountry": "US",
    "counterPartyName": "Walmart",
    "creditDebitIndicator": "DBIT",
    "currency": "USD",
    "reference": "czyo9c2n7z",
    "type": "POS",
    "typeGroup": "Payment"
  },
  {
    "amount": 345.95,
    "category": "Transfers",
    "counterPartyCountry": "US",
    "counterPartyName": "PayPal",
    "creditDebitIndicator": "CRDT",
    "currency": "USD",
    "reference": "czyo9c2n7z",
    "type": "POS",
    "typeGroup": "Payment"
  },
  {
    "amount": 25,
    "category": "Transfers",
    "counterPartyCountry": "US",
    "counterPartyName": "Jessica Biel",
    "creditDebitIndicator": "CRDT",
    "currency": "USD",
    "reference": "czyo9c2n7z",
    "type": "POS",
    "typeGroup": "Payment"
  },
  {
    "amount": 10.83,
    "category": "Shopping",
    "counterPartyCountry": "US",
    "counterPartyName": "AliExpress",
    "creditDebitIndicator": "DBIT",
    "currency": "USD",
    "reference": "czyo9c2n7z",
    "type": "POS",
    "typeGroup": "Payment"
  },
  {
    "amount": 44.59,
    "category": "Shopping",
    "counterPartyCountry": "US",
    "counterPartyName": "AliExpress",
    "creditDebitIndicator": "DBIT",
    "currency": "USD",
    "reference": "czyo9c2n7z",
    "type": "POS",
    "typeGroup": "Payment"
  },
  {
    "amount": 5.99,
    "category": "Food Drinks",
    "counterPartyCountry": "US",
    "counterPartyName": "7Eleven",
    "creditDebitIndicator": "DBIT",
    "currency": "USD",
    "reference": "czyo9c2n7z",
    "type": "POS",
    "typeGroup": "Payment"
  },
  {
    "amount": 12.54,
    "category": "Food Drinks",
    "counterPartyCountry": "US",
    "counterPartyName": "7Eleven",
    "creditDebitIndicator": "DBIT",
    "currency": "USD",
    "reference": "czyo9c2n7z",
    "type": "POS",
    "typeGroup": "Payment"
  },
  {
    "amount": 24.5,
    "category": "Hobbies Entertainment",
    "counterPartyCountry": "US",
    "counterPartyName": "AMC Theatres",
    "creditDebitIndicator": "DBIT",
    "currency": "USD",
    "reference": "czyo9c2n7z",
    "type": "POS",
    "typeGroup": "Payment"
  },
  {
    "amount": 13.1,
    "category": "Hobbies Entertainment",
    "counterPartyCountry": "US",
    "counterPartyName": "Cinemark USA, Inc.",
    "creditDebitIndicator": "DBIT",
    "currency": "USD",
    "reference": "czyo9c2n7z",
    "type": "POS",
    "typeGroup": "Payment"
  },
  {
    "amount": 67.5,
    "category": "Shopping",
    "counterPartyCountry": "US",
    "counterPartyName": "Long Beach Surf Shop",
    "creditDebitIndicator": "DBIT",
    "currency": "USD",
    "reference": "czyo9c2n7z",
    "type": "POS",
    "typeGroup": "Payment",
    "description": "Surf Lessons"
  },
  {
    "amount": 54.5,
    "category": "Hobbies Entertainment",
    "counterPartyCountry": "US",
    "counterPartyName": "Headspace",
    "creditDebitIndicator": "DBIT",
    "currency": "USD",
    "reference": "czyo9c2n7z",
    "type": "POS",
    "typeGroup": "Payment"
  },
  {
    "amount": 100,
    "category": "Transfers",
    "counterPartyCountry": "US",
    "counterPartyName": "Savings Account",
    "creditDebitIndicator": "CRDT",
    "currency": "USD",
    "reference": "czyo9c2n7z",
    "type": "POS",
    "typeGroup": "Payment"
  },
  {
    "amount": 19.99,
    "category": "Bills Utilities",
    "counterPartyCountry": "US",
    "counterPartyName": "Adobe Creative Cloud",
    "creditDebitIndicator": "DBIT",
    "currency": "USD",
    "reference": "czyo9c2n7z",
    "type": "POS",
    "typeGroup": "Payment"
  },
  {
    "amount": 119.98,
    "category": "Hobbies Entertainment",
    "counterPartyCountry": "US",
    "counterPartyName": "Ticketmaster",
    "creditDebitIndicator": "DBIT",
    "currency": "USD",
    "reference": "czyo9c2n7z",
    "type": "POS",
    "typeGroup": "Payment",
    "description": "Rolling Stones concert"
  },
  {
    "amount": 49.95,
    "category": "Shopping",
    "counterPartyCountry": "US",
    "counterPartyName": "Amazon",
    "creditDebitIndicator": "DBIT",
    "currency": "USD",
    "reference": "czyo9c2n7z",
    "type": "POS",
    "typeGroup": "Payment"
  },
  {
    "amount": 11.99,
    "category": "Hobbies Entertainment",
    "counterPartyCountry": "US",
    "counterPartyName": "YouTube Premium",
    "creditDebitIndicator": "DBIT",
    "currency": "USD",
    "reference": "czyo9c2n7z",
    "type": "POS",
    "typeGroup": "Payment"
  }
]