[
  {
    "participants": [
      {
        "admins": [
          "admin"
        ],
        "sharingUsers": false,
        "sharingAccounts": false
      }
    ]
  },
  {
    "participants": [
      {
        "admins": [
          "user"
        ],
        "sharingUsers": false,
        "sharingAccounts": false
      }
    ]
  },
  {
    "participants": [
      {
        "admins": [
          "designer"
        ],
        "sharingUsers": false,
        "sharingAccounts": false
      }
    ]
  },
  {
    "participants": [
      {
        "admins": [
          "manager"
        ],
        "sharingUsers": false,
        "sharingAccounts": false
      }
    ]
  }
]
