[
  {
    "providers": [
      {
        "admins": [
          "U0000120",
          "U0000160"
        ],
        "users": [
          "U0000120",
          "U0000160",
          "U0000140",
          "U0000141",
          "U0001000"
        ]
      }
    ],
    "consumers": [
      {
        "admins": [
          "U0000010",
          "U0000011"
        ]
      }
    ]
  },
  {
    "providers": [
      {
        "admins": [
          "U0000120"
        ],
        "users": [
          "U0000160",
          "U0000140",
          "U0000141",
          "U0001000"
        ]
      }
    ],
    "consumers": [
      {
        "admins": [
          "U0000010"
        ]
      }
    ]
  },
  {
    "providers": [
      {
        "admins": [
          "U0001001"
        ],
        "users": [
          "U0001001",
          "U0001002",
          "U0001003",
          "U0001004",
          "U0001005",
          "U0001006",
          "U0001007",
          "U0001008",
          "U0001009",
          "U0001010"
        ]
      },
      {
        "admins": [
          "U0001011"
        ],
        "users": [
          "U0001011",
          "U0001012",
          "U0001013",
          "U0001014",
          "U0001015",
          "U0001016",
          "U0001017",
          "U0001018",
          "U0001019",
          "U0001020"
        ]
      }
    ],
    "consumers": [
      {
        "admins": [
          "U0001001",
          "U0001002"
        ]
      },
      {
        "admins": [
          "U0001011",
          "U0001012"
        ]
      }
    ]
  },
  {
    "providers": [
      {
        "admins": [
          "U0001021"
        ],
        "users": [
          "U0001021",
          "U0001022",
          "U0001023",
          "U0001024",
          "U0001025",
          "U0001026",
          "U0001027",
          "U0001028",
          "U0001029",
          "U0001030"
        ]
      },
      {
        "admins": [
          "U0001011"
        ],
        "users": [
          "U0001031",
          "U0001032",
          "U0001033",
          "U0001034",
          "U0001035",
          "U0001036",
          "U0001037",
          "U0001038",
          "U0001039",
          "U0001030"
        ]
      }
    ],
    "consumers": [
      {
        "admins": [
          "U0001001",
          "U0001002"
        ]
      },
      {
        "admins": [
          "U0001011",
          "U0001012"
        ]
      }
    ]
  }
]